muffin_peewee/__init__.py
muffin_peewee/fields.py
muffin_peewee/py.typed
muffin_peewee-1.11.0.dist-info/LICENSE
muffin_peewee-1.11.0.dist-info/METADATA
muffin_peewee-1.11.0.dist-info/WHEEL
muffin_peewee-1.11.0.dist-info/top_level.txt
muffin_peewee-1.11.0.dist-info/RECORD
