Metadata-Version: 2.1
Name: muffin-peewee
Version: 1.11.0
Summary: Peewee integration for Muffin framework
Home-page: https://github.com/klen/muffin-peewee
Author: Kirill Klenov
Author-email: horneds@gmail.com
License: MIT
Project-URL: Documentation, https://github.com/klen/muffin-peewee
Project-URL: Source code, https://github.com/klen/muffin-peewee
Project-URL: Issue tracker, https://github.com/klen/muffin-peewee/issues
Keywords: peewee,sql,asyncio,trio,asgi,muffin
Platform: UNKNOWN
Classifier: Development Status :: 5 - Production/Stable
Classifier: Intended Audience :: Developers
Classifier: License :: OSI Approved :: MIT License
Classifier: Programming Language :: Python
Classifier: Programming Language :: Python :: 3
Classifier: Programming Language :: Python :: 3.7
Classifier: Programming Language :: Python :: 3.8
Classifier: Programming Language :: Python :: 3.9
Classifier: Framework :: AsyncIO
Classifier: Framework :: Trio
Requires-Python: >=3.7
Requires-Dist: aio-peewee (>=0.4.0)
Requires-Dist: muffin (>=0.83)
Requires-Dist: peewee (>=3)
Requires-Dist: peewee-migrate (>=1.4.3)
Provides-Extra: build
Requires-Dist: bump2version ; extra == 'build'
Requires-Dist: wheel ; extra == 'build'
Provides-Extra: example
Requires-Dist: uvicorn ; extra == 'example'
Provides-Extra: postgres
Requires-Dist: psycopg2-binary ; extra == 'postgres'
Provides-Extra: tests
Requires-Dist: pytest ; extra == 'tests'
Requires-Dist: pytest-aio[curio,trio] ; extra == 'tests'
Requires-Dist: pytest-mypy ; extra == 'tests'
